WikiClient/Get.py
WikiClient/__init__.py
wiki_api_client-1.0.2.dist-info/METADATA
wiki_api_client-1.0.2.dist-info/WHEEL
wiki_api_client-1.0.2.dist-info/top_level.txt
wiki_api_client-1.0.2.dist-info/RECORD
