Metadata-Version: 2.1
Name: wiki-api-client
Version: 1.0.2
Summary: Request to wiki-api.ir APIs
Home-page: https://github.com/b-3dev/python-wiki-client
Author: b-3dev
Author-email: b3dev.mmd@gmail.com
Classifier: Programming Language :: Python :: 3
Classifier: Programming Language :: Python :: 3.6
Classifier: Programming Language :: Python :: 3.7
Classifier: Programming Language :: Python :: 3.8
Classifier: Programming Language :: Python :: 3.9
Classifier: Development Status :: 5 - Production/Stable
Classifier: Operating System :: OS Independent
Classifier: Intended Audience :: Developers
Classifier: Topic :: Software Development :: Libraries
Requires-Python: >=3.6
Requires-Dist: requests
Requires-Dist: aiohttp
